MineBannerLib/__init__.py
MineBannerLib/color.py
MineBannerLib/create_banner.py
MineBannerLib/draw_image.py
MineBannerLib/layer.py
MineBannerLib/pattern.py
MineBannerLib/samples/base.png
MineBannerLib/samples/border.png
MineBannerLib/samples/bricks.png
MineBannerLib/samples/circle.png
MineBannerLib/samples/creeper.png
MineBannerLib/samples/cross.png
MineBannerLib/samples/curly_border.png
MineBannerLib/samples/diagonal_left.png
MineBannerLib/samples/diagonal_right.png
MineBannerLib/samples/diagonal_up_left.png
MineBannerLib/samples/diagonal_up_right.png
MineBannerLib/samples/flower.png
MineBannerLib/samples/globe.png
MineBannerLib/samples/gradient.png
MineBannerLib/samples/gradient_up.png
MineBannerLib/samples/half_horizontal.png
MineBannerLib/samples/half_horizontal_bottom.png
MineBannerLib/samples/half_vertical.png
MineBannerLib/samples/half_vertical_right.png
MineBannerLib/samples/mojang.png
MineBannerLib/samples/piglin.png
MineBannerLib/samples/rhombus.png
MineBannerLib/samples/skull.png
MineBannerLib/samples/small_stripes.png
MineBannerLib/samples/square_bottom_left.png
MineBannerLib/samples/square_bottom_right.png
MineBannerLib/samples/square_top_left.png
MineBannerLib/samples/square_top_right.png
MineBannerLib/samples/straight_cross.png
MineBannerLib/samples/stripe_bottom.png
MineBannerLib/samples/stripe_center.png
MineBannerLib/samples/stripe_downleft.png
MineBannerLib/samples/stripe_downright.png
MineBannerLib/samples/stripe_left.png
MineBannerLib/samples/stripe_middle.png
MineBannerLib/samples/stripe_right.png
MineBannerLib/samples/stripe_top.png
MineBannerLib/samples/triangle_bottom.png
MineBannerLib/samples/triangle_top.png
MineBannerLib/samples/triangles_bottom.png
MineBannerLib/samples/triangles_top.png
minebannerlib-0.1.0.dist-info/METADATA
minebannerlib-0.1.0.dist-info/WHEEL
minebannerlib-0.1.0.dist-info/top_level.txt
minebannerlib-0.1.0.dist-info/RECORD
